haystack_integrations/components/embedders/instructor_embedders/__init__.py
haystack_integrations/components/embedders/instructor_embedders/instructor_document_embedder.py
haystack_integrations/components/embedders/instructor_embedders/instructor_text_embedder.py
haystack_integrations/components/embedders/instructor_embedders/embedding_backend/__init__.py
haystack_integrations/components/embedders/instructor_embedders/embedding_backend/instructor_backend.py
instructor_embedders_haystack-0.4.1.dist-info/METADATA
instructor_embedders_haystack-0.4.1.dist-info/WHEEL
instructor_embedders_haystack-0.4.1.dist-info/licenses/LICENSE.txt
instructor_embedders_haystack-0.4.1.dist-info/RECORD
