Metadata-Version: 2.3
Name: instructor-embedders-haystack
Version: 0.4.1
Summary: Haystack 2.x component to embed strings and Documents using Instructor embedding model.
Project-URL: Documentation, https://github.com/deepset-ai/haystack-core-integrations/tree/main/integrations/instructor_embedders#readme
Project-URL: Issues, https://github.com/deepset-ai/haystack-core-integrations/issues
Project-URL: Source, https://github.com/deepset-ai/haystack-core-integrations/tree/main/integrations/instructor_embedders
Author-email: deepset GmbH <info@deepset.ai>
License-Expression: Apache-2.0
License-File: LICENSE.txt
Classifier: Development Status :: 4 - Beta
Classifier: License :: OSI Approved :: Apache Software License
Classifier: Programming Language :: Python
Classifier: Programming Language :: Python :: 3.8
Classifier: Programming Language :: Python :: 3.9
Classifier: Programming Language :: Python :: 3.10
Classifier: Programming Language :: Python :: 3.11
Classifier: Programming Language :: Python :: Implementation :: CPython
Classifier: Programming Language :: Python :: Implementation :: PyPy
Requires-Python: >=3.8
Requires-Dist: datasets>=2.2.0
Requires-Dist: haystack-ai
Requires-Dist: huggingface-hub<0.26.0
Requires-Dist: instructorembedding
Requires-Dist: jsonlines
Requires-Dist: numpy
Requires-Dist: requests>=2.26.0
Requires-Dist: rich
Requires-Dist: scikit-learn>=1.0.2
Requires-Dist: scipy
Requires-Dist: sentence-transformers<2.3.0,>=2.2.0
Requires-Dist: torch
Requires-Dist: tqdm
Provides-Extra: dev
Requires-Dist: pytest; extra == 'dev'
